<?xml version="1.0" encoding="utf-8"?>
<search>
  
  
  
  <entry>
    <title>UCAS-Galactic Astronomy</title>
    <link href="/2022/11/10/en/galaxies/"/>
    <url>/2022/11/10/en/galaxies/</url>
    
    <content type="html"><![CDATA[<p>The English information has not been added, please refer to <a href="/2022/11/09/zh-CN/%E6%98%9F%E7%B3%BB%E5%A4%A9%E6%96%87%E5%AD%A6/">Chinese</a> pages.</p>]]></content>
    
    
    <categories>
      
      <category>UCAS</category>
      
    </categories>
    
    
    <tags>
      
      <tag>天文</tag>
      
      <tag>学习</tag>
      
      <tag>postgraduate</tag>
      
    </tags>
    
  </entry>
  
  
  
  <entry>
    <title>Hello World-The first time to build a blog</title>
    <link href="/2022/11/10/en/hello-world/"/>
    <url>/2022/11/10/en/hello-world/</url>
    
    <content type="html"><![CDATA[<p>The English information has not been added, please refer to <a href="/2022/11/08/zh-CN/hello-world/">Chinese</a> pages.</p>]]></content>
    
    
    <categories>
      
      <category>个人博客</category>
      
    </categories>
    
    
    <tags>
      
      <tag>博客</tag>
      
      <tag>code</tag>
      
    </tags>
    
  </entry>
  
  
  
  
</search>
